LICENSE
README.md
setup.py
alpino_query/__init__.py
alpino_query/__main__.py
alpino_query/marker.py
alpino_query/parser.py
alpino_query/py.typed
alpino_query/subtree.py
alpino_query/xpath_generator.py
alpino_query.egg-info/PKG-INFO
alpino_query.egg-info/SOURCES.txt
alpino_query.egg-info/dependency_links.txt
alpino_query.egg-info/entry_points.txt
alpino_query.egg-info/requires.txt
alpino_query.egg-info/top_level.txt
alpino_query.egg-info/zip-safe