Metadata-Version: 2.1
Name: alpino-query
Version: 2.1.12
Summary: Generating XPATH queries based on a Dutch Alpino syntax tree and user-specified token properties.
Home-page: https://github.com/CentreForDigitalHumanities/alpino-query
Author: Digital Humanities Lab, Utrecht University
Author-email: digitalhumanities@uu.nl
License: CC BY-NC-SA 4.0
Platform: UNKNOWN
Requires-Python: >=3.7, <4
License-File: LICENSE
